plinx/__init__.py
plinx/applications.py
plinx/methods.py
plinx/middleware.py
plinx/response.py
plinx/status_codes.py
plinx/utils.py
plinx/orm/__init__.py
plinx/orm/orm.py
plinx/orm/utils.py
plinx-1.0.1.dist-info/licenses/LICENSE
plinx-1.0.1.dist-info/METADATA
plinx-1.0.1.dist-info/WHEEL
plinx-1.0.1.dist-info/top_level.txt
plinx-1.0.1.dist-info/RECORD
