Metadata-Version: 2.4
Name: Plinx
Version: 1.0.1
Summary: Plinx is an experimental, minimalistic, and extensible web framework and ORM written in Python.
Home-page: https://github.com/dhavalsavalia/plinx
Author: Dhaval Savalia
Author-email: coder@dhavalsavalia.com
License: MIT
Classifier: License :: OSI Approved :: MIT License
Classifier: Programming Language :: Python
Classifier: Programming Language :: Python :: 3
Classifier: Programming Language :: Python :: 3.11
Classifier: Programming Language :: Python :: Implementation :: CPython
Classifier: Programming Language :: Python :: Implementation :: PyPy
Requires-Python: >=3.11.0
License-File: LICENSE
Requires-Dist: webob
Requires-Dist: parse
Requires-Dist: requests
Requires-Dist: requests-wsgi-adapter
Dynamic: author
Dynamic: author-email
Dynamic: classifier
Dynamic: description
Dynamic: description-content-type
Dynamic: home-page
Dynamic: license
Dynamic: license-file
Dynamic: requires-dist
Dynamic: requires-python
Dynamic: summary
